<annotation>
	<folder>imgs</folder>
	<filename>dmn_ex03_005.jpeg</filename>
	<path>D:\Biblioteki\Puplit\Magisterka\imgs\dmn_ex03_005.jpeg</path>
	<source>
		<database>Unknown</database>
	</source>
	<size>
		<width>3569</width>
		<height>2551</height>
		<depth>3</depth>
	</size>
	<segmented>0</segmented>
	<object>
		<name>node_decision</name>
		<pose>Unspecified</pose>
		<truncated>0</truncated>
		<difficult>0</difficult>
		<bndbox>
			<xmin>2080</xmin>
			<ymin>140</ymin>
			<xmax>3043</xmax>
			<ymax>435</ymax>
		</bndbox>
	</object>
	<object>
		<name>node_decision</name>
		<pose>Unspecified</pose>
		<truncated>0</truncated>
		<difficult>0</difficult>
		<bndbox>
			<xmin>2070</xmin>
			<ymin>704</ymin>
			<xmax>3038</xmax>
			<ymax>977</ymax>
		</bndbox>
	</object>
	<object>
		<name>node_input_data</name>
		<pose>Unspecified</pose>
		<truncated>0</truncated>
		<difficult>0</difficult>
		<bndbox>
			<xmin>2072</xmin>
			<ymin>1209</ymin>
			<xmax>2828</xmax>
			<ymax>1448</ymax>
		</bndbox>
	</object>
	<object>
		<name>node_knowledge_model</name>
		<pose>Unspecified</pose>
		<truncated>0</truncated>
		<difficult>0</difficult>
		<bndbox>
			<xmin>365</xmin>
			<ymin>164</ymin>
			<xmax>1417</xmax>
			<ymax>480</ymax>
		</bndbox>
	</object>
	<object>
		<name>arrow_knowledge_requirement</name>
		<pose>Unspecified</pose>
		<truncated>0</truncated>
		<difficult>0</difficult>
		<bndbox>
			<xmin>1404</xmin>
			<ymin>248</ymin>
			<xmax>2080</xmax>
			<ymax>351</ymax>
		</bndbox>
	</object>
	<object>
		<name>arrow_information_requirement</name>
		<pose>Unspecified</pose>
		<truncated>0</truncated>
		<difficult>0</difficult>
		<bndbox>
			<xmin>2507</xmin>
			<ymin>430</ymin>
			<xmax>2601</xmax>
			<ymax>727</ymax>
		</bndbox>
	</object>
	<object>
		<name>arrow_information_requirement</name>
		<pose>Unspecified</pose>
		<truncated>0</truncated>
		<difficult>0</difficult>
		<bndbox>
			<xmin>2388</xmin>
			<ymin>961</ymin>
			<xmax>2507</xmax>
			<ymax>1209</ymax>
		</bndbox>
	</object>
	<object>
		<name>text</name>
		<pose>Unspecified</pose>
		<truncated>0</truncated>
		<difficult>0</difficult>
		<bndbox>
			<xmin>462</xmin>
			<ymin>238</ymin>
			<xmax>1346</xmax>
			<ymax>398</ymax>
		</bndbox>
	</object>
	<object>
		<name>text</name>
		<pose>Unspecified</pose>
		<truncated>0</truncated>
		<difficult>0</difficult>
		<bndbox>
			<xmin>2151</xmin>
			<ymin>219</ymin>
			<xmax>2909</xmax>
			<ymax>369</ymax>
		</bndbox>
	</object>
	<object>
		<name>text</name>
		<pose>Unspecified</pose>
		<truncated>0</truncated>
		<difficult>0</difficult>
		<bndbox>
			<xmin>2122</xmin>
			<ymin>769</ymin>
			<xmax>2957</xmax>
			<ymax>909</ymax>
		</bndbox>
	</object>
	<object>
		<name>text</name>
		<pose>Unspecified</pose>
		<truncated>0</truncated>
		<difficult>0</difficult>
		<bndbox>
			<xmin>2141</xmin>
			<ymin>1254</ymin>
			<xmax>2696</xmax>
			<ymax>1401</ymax>
		</bndbox>
	</object>
</annotation>
