<annotation>
	<folder>to_label</folder>
	<filename>dmn_ex04_009.jpeg</filename>
	<path>C:\Users\lj6gv9\Desktop\to_label\dmn_ex04_009.jpeg</path>
	<source>
		<database>Unknown</database>
	</source>
	<size>
		<width>3569</width>
		<height>2551</height>
		<depth>3</depth>
	</size>
	<segmented>0</segmented>
	<object>
		<name>node_decision</name>
		<pose>Unspecified</pose>
		<truncated>0</truncated>
		<difficult>0</difficult>
		<bndbox>
			<xmin>2713</xmin>
			<ymin>1356</ymin>
			<xmax>3362</xmax>
			<ymax>1610</ymax>
		</bndbox>
	</object>
	<object>
		<name>node_decision</name>
		<pose>Unspecified</pose>
		<truncated>0</truncated>
		<difficult>0</difficult>
		<bndbox>
			<xmin>1570</xmin>
			<ymin>1348</ymin>
			<xmax>2124</xmax>
			<ymax>1604</ymax>
		</bndbox>
	</object>
	<object>
		<name>node_input_data</name>
		<pose>Unspecified</pose>
		<truncated>0</truncated>
		<difficult>0</difficult>
		<bndbox>
			<xmin>1005</xmin>
			<ymin>1861</ymin>
			<xmax>1751</xmax>
			<ymax>2131</ymax>
		</bndbox>
	</object>
	<object>
		<name>node_knowledge_model</name>
		<pose>Unspecified</pose>
		<truncated>0</truncated>
		<difficult>0</difficult>
		<bndbox>
			<xmin>2059</xmin>
			<ymin>1880</ymin>
			<xmax>2865</xmax>
			<ymax>2156</ymax>
		</bndbox>
	</object>
	<object>
		<name>text</name>
		<pose>Unspecified</pose>
		<truncated>0</truncated>
		<difficult>0</difficult>
		<bndbox>
			<xmin>1624</xmin>
			<ymin>1394</ymin>
			<xmax>2054</xmax>
			<ymax>1556</ymax>
		</bndbox>
	</object>
	<object>
		<name>text</name>
		<pose>Unspecified</pose>
		<truncated>0</truncated>
		<difficult>0</difficult>
		<bndbox>
			<xmin>2784</xmin>
			<ymin>1394</ymin>
			<xmax>3303</xmax>
			<ymax>1548</ymax>
		</bndbox>
	</object>
	<object>
		<name>text</name>
		<pose>Unspecified</pose>
		<truncated>0</truncated>
		<difficult>0</difficult>
		<bndbox>
			<xmin>2124</xmin>
			<ymin>1942</ymin>
			<xmax>2776</xmax>
			<ymax>2088</ymax>
		</bndbox>
	</object>
	<object>
		<name>text</name>
		<pose>Unspecified</pose>
		<truncated>0</truncated>
		<difficult>0</difficult>
		<bndbox>
			<xmin>1081</xmin>
			<ymin>1915</ymin>
			<xmax>1659</xmax>
			<ymax>2069</ymax>
		</bndbox>
	</object>
	<object>
		<name>arrow_information_requirement</name>
		<pose>Unspecified</pose>
		<truncated>0</truncated>
		<difficult>0</difficult>
		<bndbox>
			<xmin>1603</xmin>
			<ymin>1585</ymin>
			<xmax>1759</xmax>
			<ymax>1894</ymax>
		</bndbox>
	</object>
	<object>
		<name>arrow_information_requirement</name>
		<pose>Unspecified</pose>
		<truncated>0</truncated>
		<difficult>0</difficult>
		<bndbox>
			<xmin>1732</xmin>
			<ymin>1534</ymin>
			<xmax>2730</xmax>
			<ymax>1937</ymax>
		</bndbox>
	</object>
	<object>
		<name>arrow_knowledge_requirement</name>
		<pose>Unspecified</pose>
		<truncated>0</truncated>
		<difficult>0</difficult>
		<bndbox>
			<xmin>1919</xmin>
			<ymin>1575</ymin>
			<xmax>2257</xmax>
			<ymax>1904</ymax>
		</bndbox>
	</object>
</annotation>
